.DS_Store
pyframe/__init__.py
pyframe/app.py
pyframe/middleware.py
pyframe/response.py
pynova/__init__.py
pynova/app.py
pynova/middleware.py
pynova/response.py
pywebhive/__init__.py
pywebhive/app.py
pywebhive/middleware.py
pywebhive/response.py
pywebhive-0.1.1.dist-info/METADATA
pywebhive-0.1.1.dist-info/WHEEL
pywebhive-0.1.1.dist-info/top_level.txt
pywebhive-0.1.1.dist-info/RECORD
