Metadata-Version: 2.1
Name: pywebhive
Version: 0.1.1
Summary: Python web framework built for learning purposes
Home-page: https://github.com/shaxzod02/py-web-hive
Author: Shakhzod Okhunjonov
Author-email: shakhzodokhunjonov@gmail.com
License: MIT
Platform: UNKNOWN
Classifier: License :: OSI Approved :: MIT License
Classifier: Programming Language :: Python
Classifier: Programming Language :: Python :: 3
Classifier: Programming Language :: Python :: 3.6
Classifier: Programming Language :: Python :: Implementation :: CPython
Classifier: Programming Language :: Python :: Implementation :: PyPy
Requires-Python: >=3.9.0
Requires-Dist: Jinja2==3.1.5
Requires-Dist: parse==1.20.2
Requires-Dist: WebOb==1.8.9
Requires-Dist: whitenoise==6.8.2
Requires-Dist: requests==2.32.3
Requires-Dist: requests-wsgi-adapter==0.4.1
